deepagents/__init__.py
deepagents/graph.py
deepagents/realtimex_graph.py
deepagents/backends/__init__.py
deepagents/backends/composite.py
deepagents/backends/filesystem.py
deepagents/backends/protocol.py
deepagents/backends/sandbox.py
deepagents/backends/state.py
deepagents/backends/store.py
deepagents/backends/utils.py
deepagents/middleware/__init__.py
deepagents/middleware/filesystem.py
deepagents/middleware/patch_tool_calls.py
deepagents/middleware/subagents.py
deepagents/realtimex_middleware/__init__.py
deepagents/realtimex_middleware/agent_memory.py
deepagents/realtimex_middleware/skills/__init__.py
deepagents/realtimex_middleware/skills/load.py
deepagents/realtimex_middleware/skills/middleware.py
realtimex_deepagents-0.4.2.dist-info/METADATA
realtimex_deepagents-0.4.2.dist-info/WHEEL
realtimex_deepagents-0.4.2.dist-info/top_level.txt
realtimex_deepagents-0.4.2.dist-info/RECORD
